fairlens/__init__.py
fairlens/scorer.py
fairlens/utils.py
fairlens/version.py
fairlens/metrics/__init__.py
fairlens/metrics/correlation.py
fairlens/metrics/distance.py
fairlens/metrics/significance.py
fairlens/metrics/unified.py
fairlens/plot/__init__.py
fairlens/plot/distr.py
fairlens/plot/heatmap.py
fairlens/plot/style.py
fairlens/sensitive/__init__.py
fairlens/sensitive/correlation.py
fairlens/sensitive/detection.py
fairlens/sensitive/configs/config_engb.json
fairlens/sensitive/configs/config_mock.json
fairlens-0.1.0.dist-info/LICENSE.md
fairlens-0.1.0.dist-info/METADATA
fairlens-0.1.0.dist-info/WHEEL
fairlens-0.1.0.dist-info/top_level.txt
fairlens-0.1.0.dist-info/RECORD
