Metadata-Version: 2.1
Name: fairlens
Version: 0.1.0
Summary: Identify bias and measure fairness of your data
Home-page: https://github.com/synthesized-io/fairlens
Author: Synthesized Ltd.
Author-email: team@synthesized.io
Maintainer: Synthesized Ltd.
License: 'BSD 3-Clause License'
Project-URL: Company, https://synthesized.io
Platform: UNKNOWN
Classifier: License :: OSI Approved :: BSD License
Classifier: Development Status :: 4 - Beta
Classifier: Programming Language :: Python :: 3.6
Classifier: Programming Language :: Python :: 3.7
Classifier: Programming Language :: Python :: 3.8
Classifier: Programming Language :: Python :: 3.9
Classifier: Operating System :: Microsoft :: Windows
Classifier: Operating System :: Unix
Classifier: Operating System :: MacOS
Classifier: Intended Audience :: Developers
Classifier: Intended Audience :: Science/Research
Requires-Python: >=3.6
License-File: LICENSE.md
Requires-Dist: numpy (>=1.18.4)
Requires-Dist: pandas (>=1.1.5)
Requires-Dist: scipy (>=1.5.4)
Requires-Dist: scikit-learn (>=0.23.2)
Requires-Dist: matplotlib (>=2.1.0)
Requires-Dist: seaborn (>=0.11.1)
Requires-Dist: dcor (>=0.5.3)
Requires-Dist: pyemd (==0.5.1)
Provides-Extra: dev
Requires-Dist: pre-commit ; extra == 'dev'
Provides-Extra: doc
Requires-Dist: sphinx (==3.5.4) ; extra == 'doc'
Requires-Dist: ipython (==7.23.1) ; extra == 'doc'
Requires-Dist: m2r2 (==0.2.7) ; extra == 'doc'
Requires-Dist: pydata-sphinx-theme (==0.6.3) ; extra == 'doc'
Requires-Dist: sphinx-panels (==0.6.0) ; extra == 'doc'
Requires-Dist: sphinxcontrib-bibtex (==2.3.0) ; extra == 'doc'
Provides-Extra: test
Requires-Dist: pytest (>=6) ; extra == 'test'
Requires-Dist: pytest-cov (>=2) ; extra == 'test'
